nmf_torch-0.1.1.dist-info/WHEEL
nmf_torch-0.1.1.dist-info/RECORD
nmf_torch-0.1.1.dist-info/LICENSE
nmf_torch-0.1.1.dist-info/top_level.txt
nmf_torch-0.1.1.dist-info/METADATA
nmf/nmf.py
nmf/__init__.py
nmf/utils/_nnls_bpp.py
nmf/utils/__init__.py
nmf/inmf_models/_inmf_batch_mu.py
nmf/inmf_models/_inmf_online_hals.py
nmf/inmf_models/_inmf_batch_base.py
nmf/inmf_models/_inmf_online_nnls_bpp.py
nmf/inmf_models/_inmf_online_base.py
nmf/inmf_models/_inmf_batch_hals.py
nmf/inmf_models/_inmf_base.py
nmf/inmf_models/_inmf_online_mu.py
nmf/inmf_models/__init__.py
nmf/inmf_models/_inmf_batch_nnls_bpp.py
nmf/cylib/nnls_bpp_utils.cpython-38-x86_64-linux-gnu.so
nmf/nmf_models/_nmf_batch_nnls_bpp.py
nmf/nmf_models/_nmf_base.py
nmf/nmf_models/_nmf_online_mu.py
nmf/nmf_models/_nmf_online_base.py
nmf/nmf_models/_nmf_batch_hals.py
nmf/nmf_models/_nmf_batch_base.py
nmf/nmf_models/_nmf_online_nnls_bpp.py
nmf/nmf_models/_nmf_online_hals.py
nmf/nmf_models/__init__.py
nmf/nmf_models/_nmf_batch_mu.py
